gepeto/__init__.py
gepeto/agents/__init__.py
gepeto/agents/agents.py
gepeto/agents/schema.py
gepeto/client/__init__.py
gepeto/client/client.py
gepeto/prompts/__init__.py
gepeto/prompts/prompts.py
gepeto/prompts/schema.py
gepeto/repl/__init__.py
gepeto/repl/repl.py
gepeto/team/__init__.py
gepeto/team/schema.py
gepeto/team/team.py
gepeto/team/utils.py
gepeto/team/schemas/__init__.py
gepeto/team/schemas/agent_schema.py
gepeto-1.1.23.dist-info/METADATA
gepeto-1.1.23.dist-info/WHEEL
gepeto-1.1.23.dist-info/top_level.txt
gepeto-1.1.23.dist-info/RECORD
