Metadata-Version: 2.4
Name: gepeto
Version: 1.1.23
Summary: pip install gepeto
Home-page: https://github.com/gepetoai/gepeto
Author: Uzair
Author-email: uzair@hellogepeto.com
Requires-Dist: numpy>=2.2.0
Requires-Dist: pytest
Requires-Dist: requests>=2.32.0
Requires-Dist: tqdm>=4.65.0
Requires-Dist: pre-commit>=4.0.0
Requires-Dist: instructor>=1.7.0
Requires-Dist: litellm>=1.49.1
Dynamic: author
Dynamic: author-email
Dynamic: description
Dynamic: description-content-type
Dynamic: home-page
Dynamic: requires-dist
Dynamic: summary
